{
  "cate": "1",
  "date": "1æ29æ¥ 19æ15å",
  "datetime": "2018-01-29T19:15",
  "video": "",
  "duration": 0,
  "img": "html/20180129/K10011307031_1801291755_1801291836_01_02.jpg",
  "title": "「チャイルドロック」使用せず ドラム式洗濯機で男児死亡",
  "summary": "２７日、大阪・堺市の住宅で５歳の男の子がドラム式の洗濯乾燥機の中で見つかり死亡した事故で、当時、子どもが誤って入るのを防ぐ「チャイルドロック」という機能が使われていなかったことが警察への取材でわかりました。消費者庁は、こうした機能を利用するよう呼びかけています。",
  "more": "２７日、大阪・堺市堺区の住宅でこの家に住む５歳の男の子がドラム式の洗濯乾燥機の中でぐったりしているのが見つかり、病院に運ばれましたが死亡しました。<br /><br />警察によりますと、男の子は身長がおよそ１メートル２０センチで、床からの高さが４０センチの位置にある洗濯槽の中に自分で入ったあとドアが閉まって出られなくなったと見られ、死因は窒息死だったということです。<br /><br />また、この洗濯乾燥機にはボタン操作でドアをロックし、子どもが誤って入るのを防ぐ「チャイルドロック」という機能が付いていましたが、当時、この機能は使われていなかったということです。<br /><br />ドラム式の洗濯乾燥機をめぐっては、３年前にも東京都内で７歳の男の子が閉じ込められて死亡する事故が起きていて、消費者庁は、ふだんからドアを閉めておくことや、チャイルドロックを利用すること、また、チャイルドロックがない場合は洗濯機の両サイドにフックを取り付けてゴムバンドで開かないようにするなどの対策を取るよう呼びかけています。",
  "body": [
    {
      "title": "",
      "img": "",
      "align": "",
      "text": "",
      "textPos": ""
    }
  ],
  "relationNews": [
    {
      "link": "html/20180128/k10011305931000.html",
      "title": "ドラム式洗濯乾燥機の中で５歳男児死亡 大阪 堺",
      "date": "1月28日  12時44分",
      "datetime": "2018-01-28T12:44",
      "imgPath": "html/20180128/K10011305931_1801281944_1801281947_01_03.jpg",
      "iconPath": "html/20180128/K10011305931_1801281944_1801281947_02_01.jpg",
      "video": "https://www3.nhk.or.jp/news/html/20180128/movie/k10011305931_201801281944_201801281947.html",
      "duration": 37
    }
  ],
  "relationLink": [],
  "word": [],
  "news_id": "k10011307031000",
  "yyyy": "2018",
  "mm": "01",
  "dd": "29",
  "url": "https://www3.nhk.or.jp/news/html/20180129/k10011307031000.html"
}