{
  "cate": "5",
  "date": "1æ23æ¥ 7æ24å",
  "datetime": "2018-01-23T07:24",
  "video": "",
  "duration": 0,
  "img": "html/20180123/K10011298581_1801230710_1801230724_01_02.jpg",
  "title": "米アマゾン レジがない無人コンビニ店舗を開店",
  "summary": "アメリカのネット通販大手のアマゾン・ドット・コムは、西海岸のシアトルで、棚から商品を取り出し外に出るだけで自動的にクレジットカードで決済される無人のコンビニをオープンし、レジがないことから小売りの在り方を大きく変える可能性があるとして注目されています。",
  "more": "アマゾン・ドット・コムは、ワシントン州シアトルにある本社の敷地内に２２日、飲み物やサンドイッチなどを販売する無人のコンビニをオープンしました。<br /><br />利用者は、スマートフォンにダウンロードした専用のアプリを駅の自動改札のような機械にかざして店に入り、棚から商品を取り出してそのまま外に出ると、あらかじめ登録されたクレジットカードで決済されます。最大の特徴はレジがないことで、買い物かごもありません。<br /><br />天井に設置された大量のカメラや棚に備え付けられたセンサーがどの客がどの商品を選んだかを常に把握していて、アマゾンは「自動運転と同じように、ＡＩ＝人工知能を使って画像認識と機械学習の仕組みを駆使している」と説明しています。<br /><br />アマゾンは去年、高級スーパーを買収するなど、実際の店舗の事業にも乗り出しています。<br /><br />現地のメディアによりますと、無人店舗の技術をほかで活用する計画は今のところないということですが、レジのない店舗のオープンは小売りの在り方を大きく変える可能性があるとして注目されています。",
  "body": [
    {
      "title": "",
      "img": "",
      "align": "",
      "text": "",
      "textPos": ""
    }
  ],
  "relationNews": [
    {
      "link": "html/20180119/k10011294151000.html",
      "title": "５万人の雇用生むか 米アマゾン 第２本社の建設予定地選定",
      "date": "1月19日  6時35分",
      "datetime": "2018-01-19T06:35",
      "imgPath": "html/20180119/K10011294151_1801190702_1801190711_01_02.jpg",
      "iconPath": "html/20180119/K10011294151_1801190702_1801190711_02_01.jpg",
      "video": "",
      "duration": 0
    }
  ],
  "relationLink": [
    {
      "link": "https://www3.nhk.or.jp/news/business_tokushu/2017_1108.html?utm_int=tokushu-business_contents_list-items_048",
      "title": "どうなる？未来のコンビニ",
      "time": "ビジネス特集 11月8日",
      "datetime": "2017-11-08"
    },
    {
      "link": "http://www.nhk.or.jp/kaisetsu-blog/700/268477.html",
      "title": "「進むロボットの“採用”仕事はどう変わる？」（くらし☆解説）",
      "time": "解説委員室ブログ 4月19日",
      "datetime": "2017-04-19"
    }
  ],
  "word": [
    {
      "link": "word/0000009.html",
      "title": "IT・ネット"
    }
  ],
  "news_id": "k10011298581000",
  "yyyy": "2018",
  "mm": "01",
  "dd": "23",
  "url": "https://www3.nhk.or.jp/news/html/20180123/k10011298581000.html"
}